{
  "parent": "minecraft:recipes/root",
  "criteria": {
    "has_the_recipe": {
      "conditions": {
        "recipe": "simpletungsten:prasinos_nugget_from_smelting"
      },
      "trigger": "minecraft:recipe_unlocked"
    },
    "prasinos_nugget_from_smelting": {
      "conditions": {
        "items": [
          {
            "items": [
              "simpletungsten:prasinos_axe"
            ]
          }
        ]
      },
      "trigger": "minecraft:inventory_changed"
    }
  },
  "requirements": [
    [
      "prasinos_nugget_from_smelting",
      "has_the_recipe"
    ]
  ],
  "rewards": {
    "recipes": [
      "simpletungsten:prasinos_nugget_from_smelting"
    ]
  },
  "sends_telemetry_event": false
}